hotxlfp/__init__.py
hotxlfp/parser.py
hotxlfp/tinyemitter.py
hotxlfp/_compat/__init__.py
hotxlfp/_compat/py3/__init__.py
hotxlfp/_compat/py3/statistics.py
hotxlfp/formulas/__init__.py
hotxlfp/formulas/dateandtime.py
hotxlfp/formulas/engineering.py
hotxlfp/formulas/error.py
hotxlfp/formulas/financial.py
hotxlfp/formulas/information.py
hotxlfp/formulas/logic.py
hotxlfp/formulas/lookupandreference.py
hotxlfp/formulas/mathtrig.py
hotxlfp/formulas/operators.py
hotxlfp/formulas/statistical.py
hotxlfp/formulas/text.py
hotxlfp/formulas/utils.py
hotxlfp/grammarparser/__init__.py
hotxlfp/grammarparser/lexer.py
hotxlfp/grammarparser/parser.py
hotxlfp/grammarparser/parser_FormulaParser_parsetab.py
hotxlfp/helper/__init__.py
hotxlfp/helper/cell.py
hotxlfp/helper/number.py
hotxlfp-1.0.2.dist-info/LICENSE
hotxlfp-1.0.2.dist-info/METADATA
hotxlfp-1.0.2.dist-info/WHEEL
hotxlfp-1.0.2.dist-info/top_level.txt
hotxlfp-1.0.2.dist-info/RECORD
