Metadata-Version: 2.1
Name: hotxlfp
Version: 1.0.2
Home-page: https://github.com/aidhound/hotxlfp
Download-URL: https://github.com/aidhound/hotxlfp/archive/1.0.2.tar.gz
Author: Leonel Câmara
Author-email: leonelcamara@gmail.com
License: MIT
Keywords: excel,formula,parser
Classifier: Development Status :: 4 - Beta
Classifier: Intended Audience :: Developers
Classifier: License :: OSI Approved :: MIT License
Classifier: Programming Language :: Python :: 3.6
Classifier: Programming Language :: Python :: 3.7
Classifier: Programming Language :: Python :: 3.8
Classifier: Programming Language :: Python :: 3.9
Classifier: Programming Language :: Python :: 3.10
Classifier: Programming Language :: Python :: 3.11
License-File: LICENSE
Requires-Dist: ply
Requires-Dist: python-dateutil
